oidc/__init__.py
oidc/apps.py
oidc/constants.py
oidc/provider.py
oidc/templates/oidc/configure.html
oidc/views.py
infinitum_sentry_auth_oidc-6.0.1.dist-info/entry_points.txt
infinitum_sentry_auth_oidc-6.0.1.dist-info/LICENSE
infinitum_sentry_auth_oidc-6.0.1.dist-info/WHEEL
infinitum_sentry_auth_oidc-6.0.1.dist-info/METADATA
infinitum_sentry_auth_oidc-6.0.1.dist-info/RECORD
