Metadata-Version: 2.1
Name: infinitum-sentry-auth-oidc
Version: 6.0.1
Summary: OpenID Connect authentication provider for Sentry with disabled ssl check
License: Apache 2.0
Author: Max Wittig
Author-email: max.wittig@siemens.com
Requires-Python: >=3.6,<4.0
Classifier: Intended Audience :: Developers
Classifier: Intended Audience :: System Administrators
Classifier: License :: Other/Proprietary License
Classifier: Operating System :: OS Independent
Classifier: Programming Language :: Python :: 3
Classifier: Programming Language :: Python :: 3.10
Classifier: Programming Language :: Python :: 3.6
Classifier: Programming Language :: Python :: 3.7
Classifier: Programming Language :: Python :: 3.8
Classifier: Programming Language :: Python :: 3.9
Classifier: Topic :: Software Development
